mosmo/__init__.py
mosmo/calc/__init__.py
mosmo/calc/convenience_kinetics.py
mosmo/calc/elementary_modes.py
mosmo/calc/fba_gd.py
mosmo/calc/ph_dynamics.py
mosmo/knowledge/__init__.py
mosmo/knowledge/codecs.py
mosmo/knowledge/datasources.py
mosmo/knowledge/kb.py
mosmo/knowledge/session.py
mosmo/knowledge/thermo.py
mosmo/model/__init__.py
mosmo/model/base.py
mosmo/model/core.py
mosmo/model/pathway.py
mosmo/preso/__init__.py
mosmo/preso/escher/__init__.py
mosmo/preso/escher/escher_map.py
mosmo/preso/escher/escher_model.py
mosmo-0.2.0.dist-info/METADATA
mosmo-0.2.0.dist-info/WHEEL
mosmo-0.2.0.dist-info/licenses/LICENSE.txt
mosmo-0.2.0.dist-info/RECORD
