Metadata-Version: 2.4
Name: mosmo
Version: 0.2.0
Summary: Molecular Systems Modeling toolkit
Project-URL: Homepage, https://github.com/fdrusso/mosmo
Project-URL: Bug Tracker, https://github.com/fdrusso/mosmo/issues
Author-email: Frank D Russo <fdrusso.42@gmail.com>
License: MIT License
License-File: LICENSE.txt
Classifier: Development Status :: 3 - Alpha
Classifier: Intended Audience :: Science/Research
Classifier: License :: OSI Approved :: MIT License
Classifier: Operating System :: OS Independent
Classifier: Programming Language :: Python :: 3
Classifier: Topic :: Scientific/Engineering :: Artificial Life
Classifier: Topic :: Scientific/Engineering :: Bio-Informatics
Requires-Python: >=3.11
Requires-Dist: equilibrator-api>=0.6
Requires-Dist: jax>=0.4
Requires-Dist: numpy>=2.1
Requires-Dist: pymongo>=4.8
Requires-Dist: scipy>=1.12
Provides-Extra: deploy
Requires-Dist: hatch>=1.12; extra == 'deploy'
Provides-Extra: test
Requires-Dist: pytest>=8.3; extra == 'test'
